flask_idempotent.py
Flask_Idempotent_Memory-0.2.0.dist-info/LICENSE
Flask_Idempotent_Memory-0.2.0.dist-info/METADATA
Flask_Idempotent_Memory-0.2.0.dist-info/WHEEL
Flask_Idempotent_Memory-0.2.0.dist-info/top_level.txt
Flask_Idempotent_Memory-0.2.0.dist-info/RECORD
