Metadata-Version: 2.1
Name: Flask-Idempotent-Memory
Version: 0.2.0
Summary: Idempotent requests for Flask applications using memory only
Home-page: https://github.com/KnugiHK/flask-idempotent-memory
Author: Knugi (originally Flask-Idempotent by Franklyn Tackitt)
Author-email: info@knugi.xyz
License: MIT
Keywords: flask,api,memory,idempotent
Platform: any
Classifier: Environment :: Web Environment
Classifier: Intended Audience :: Developers
Classifier: License :: OSI Approved :: MIT License
Classifier: Operating System :: OS Independent
Classifier: Programming Language :: Python
Classifier: Topic :: Internet :: WWW/HTTP :: Dynamic Content
Classifier: Topic :: Software Development :: Libraries :: Python Modules
License-File: LICENSE
Requires-Dist: Flask (>=0.9)
